abeliantensors/__init__.py
abeliantensors/abeliantensor.py
abeliantensors/symmetrytensors.py
abeliantensors/tensor.py
abeliantensors/tensorcommon.py
abeliantensors-0.1.0.dist-info/LICENSE
abeliantensors-0.1.0.dist-info/METADATA
abeliantensors-0.1.0.dist-info/WHEEL
abeliantensors-0.1.0.dist-info/top_level.txt
abeliantensors-0.1.0.dist-info/RECORD
