Metadata-Version: 2.1
Name: abeliantensors
Version: 0.1.0
Summary: Library for Abelian symmetry preserving tensors.
Home-page: https://github.com/mhauru/abeliantensors
Author: Markus Hauru
Author-email: markus@mhauru.org
License: MIT
Keywords: tensor,tensor networks,linear algebra
Platform: UNKNOWN
Classifier: Programming Language :: Python :: 3
Classifier: License :: OSI Approved :: MIT License
Classifier: Operating System :: OS Independent
Classifier: Topic :: Scientific/Engineering
Requires-Python: >=3.6
Requires-Dist: scipy (>=1.0.0)
Provides-Extra: demo
Requires-Dist: ncon ; extra == 'demo'
Requires-Dist: timeit ; extra == 'demo'
Requires-Dist: matplotlib ; extra == 'demo'
Requires-Dist: seaborn ; extra == 'demo'
Provides-Extra: doc
Requires-Dist: sphinx ; extra == 'doc'
Requires-Dist: sphinx-rtd-theme ; extra == 'doc'
Requires-Dist: recommonmark ; extra == 'doc'
Provides-Extra: tests
Requires-Dist: ncon ; extra == 'tests'
Requires-Dist: pytest ; extra == 'tests'
Requires-Dist: pytest-randomly ; extra == 'tests'
Requires-Dist: coverage ; extra == 'tests'
